HFS_CC_PSO/__init__.py
HFS_CC_PSO/hfs_cc_pso.py
HFS_CC_PSO-0.0.1.dist-info/LICENSE
HFS_CC_PSO-0.0.1.dist-info/METADATA
HFS_CC_PSO-0.0.1.dist-info/WHEEL
HFS_CC_PSO-0.0.1.dist-info/top_level.txt
HFS_CC_PSO-0.0.1.dist-info/RECORD
